flax/__init__.py
flax/configurations.py
flax/cursor.py
flax/errors.py
flax/ids.py
flax/io.py
flax/jax_utils.py
flax/py.typed
flax/serialization.py
flax/struct.py
flax/traceback_util.py
flax/traverse_util.py
flax/typing.py
flax/version.py
flax/core/__init__.py
flax/core/axes_scan.py
flax/core/flax_functional_engine.ipynb
flax/core/frozen_dict.py
flax/core/lift.py
flax/core/meta.py
flax/core/partial_eval.py
flax/core/scope.py
flax/core/spmd.py
flax/core/tracers.py
flax/core/variables.py
flax/core/nn/__init__.py
flax/core/nn/attention.py
flax/core/nn/linear.py
flax/core/nn/normalization.py
flax/core/nn/stochastic.py
flax/experimental/__init__.py
flax/experimental/nnx.py
flax/linen/README.md
flax/linen/__init__.py
flax/linen/activation.py
flax/linen/attention.py
flax/linen/batch_apply.py
flax/linen/combinators.py
flax/linen/dtypes.py
flax/linen/fp8_ops.py
flax/linen/initializers.py
flax/linen/kw_only_dataclasses.py
flax/linen/linear.py
flax/linen/module.py
flax/linen/normalization.py
flax/linen/partitioning.py
flax/linen/pooling.py
flax/linen/recurrent.py
flax/linen/spmd.py
flax/linen/stochastic.py
flax/linen/summary.py
flax/linen/transforms.py
flax/linen/experimental/layers_with_named_axes.py
flax/metrics/__init__.py
flax/metrics/tensorboard.py
flax/nnx/README.md
flax/nnx/__init__.py
flax/nnx/extract.py
flax/nnx/filterlib.py
flax/nnx/graph.py
flax/nnx/helpers.py
flax/nnx/ids.py
flax/nnx/module.py
flax/nnx/proxy_caller.py
flax/nnx/pytreelib.py
flax/nnx/reprlib.py
flax/nnx/rnglib.py
flax/nnx/spmd.py
flax/nnx/statelib.py
flax/nnx/summary.py
flax/nnx/tracers.py
flax/nnx/traversals.py
flax/nnx/variablelib.py
flax/nnx/visualization.py
flax/nnx/bridge/__init__.py
flax/nnx/bridge/interop.py
flax/nnx/bridge/module.py
flax/nnx/bridge/variables.py
flax/nnx/bridge/wrappers.py
flax/nnx/nn/__init__.py
flax/nnx/nn/activations.py
flax/nnx/nn/attention.py
flax/nnx/nn/dtypes.py
flax/nnx/nn/initializers.py
flax/nnx/nn/linear.py
flax/nnx/nn/lora.py
flax/nnx/nn/normalization.py
flax-0.12.2.dist-info/licenses/AUTHORS
flax-0.12.2.dist-info/licenses/LICENSE
flax-0.12.2.dist-info/METADATA
flax-0.12.2.dist-info/WHEEL
flax-0.12.2.dist-info/top_level.txt
flax-0.12.2.dist-info/RECORD
