Metadata-Version: 2.4
Name: flax
Version: 0.12.2
Summary: Flax: A neural network library for JAX designed for flexibility
Author-email: Flax team <flax-dev@google.com>
Project-URL: homepage, https://github.com/google/flax
Classifier: Development Status :: 3 - Alpha
Classifier: Intended Audience :: Developers
Classifier: Intended Audience :: Science/Research
Classifier: License :: OSI Approved :: Apache Software License
Classifier: Programming Language :: Python :: 3.11
Classifier: Programming Language :: Python :: 3.12
Classifier: Topic :: Scientific/Engineering :: Artificial Intelligence
Requires-Python: >=3.11
License-File: LICENSE
License-File: AUTHORS
Requires-Dist: numpy>=1.23.2; python_version >= "3.11"
Requires-Dist: numpy>=1.26.0; python_version >= "3.12"
Requires-Dist: jax>=0.8.1
Requires-Dist: msgpack
Requires-Dist: optax
Requires-Dist: orbax-checkpoint
Requires-Dist: tensorstore
Requires-Dist: rich>=11.1
Requires-Dist: typing_extensions>=4.2
Requires-Dist: PyYAML>=5.4.1
Requires-Dist: treescope>=0.1.7
Provides-Extra: testing
Requires-Dist: clu; extra == "testing"
Requires-Dist: clu<=0.0.9; python_version < "3.10" and extra == "testing"
Requires-Dist: einops; extra == "testing"
Requires-Dist: gymnasium[atari]; extra == "testing"
Requires-Dist: jaxlib; extra == "testing"
Requires-Dist: jaxtyping; extra == "testing"
Requires-Dist: jraph>=0.0.6dev0; extra == "testing"
Requires-Dist: ml-collections; extra == "testing"
Requires-Dist: mypy; extra == "testing"
Requires-Dist: opencv-python; extra == "testing"
Requires-Dist: protobuf<6; python_version >= "3.13" and extra == "testing"
Requires-Dist: pytest; extra == "testing"
Requires-Dist: pytest-cov; extra == "testing"
Requires-Dist: pytest-custom_exit_code; extra == "testing"
Requires-Dist: pytest-xdist; extra == "testing"
Requires-Dist: pytype; extra == "testing"
Requires-Dist: sentencepiece==0.2.0; extra == "testing"
Requires-Dist: tensorflow_text>=2.11.0; (platform_system != "Darwin" and python_version < "3.13") and extra == "testing"
Requires-Dist: tensorflow_datasets; extra == "testing"
Requires-Dist: tensorflow>=2.12.0; python_version < "3.13" and extra == "testing"
Requires-Dist: tensorflow>=2.20.0; python_version >= "3.13" and extra == "testing"
Requires-Dist: keras<3.13; extra == "testing"
Requires-Dist: torch; extra == "testing"
Requires-Dist: treescope>=0.1.1; python_version >= "3.10" and extra == "testing"
Requires-Dist: cloudpickle>=3.0.0; extra == "testing"
Requires-Dist: ale-py>=0.10.2; extra == "testing"
Provides-Extra: docs
Requires-Dist: sphinx==6.2.1; extra == "docs"
Requires-Dist: sphinx-book-theme; extra == "docs"
Requires-Dist: Pygments>=2.6.1; extra == "docs"
Requires-Dist: ipykernel; extra == "docs"
Requires-Dist: myst_nb; extra == "docs"
Requires-Dist: nbstripout; extra == "docs"
Requires-Dist: recommonmark; extra == "docs"
Requires-Dist: ipython_genutils; extra == "docs"
Requires-Dist: sphinx-design; extra == "docs"
Requires-Dist: jupytext==1.13.8; extra == "docs"
Requires-Dist: dm-haiku>=0.0.14; extra == "docs"
Requires-Dist: docutils; extra == "docs"
Requires-Dist: matplotlib; extra == "docs"
Requires-Dist: scikit-learn; extra == "docs"
Requires-Dist: ml_collections; extra == "docs"
Requires-Dist: einops; extra == "docs"
Requires-Dist: kagglehub>=0.3.3; extra == "docs"
Requires-Dist: ipywidgets>=8.1.5; extra == "docs"
Provides-Extra: dev
Requires-Dist: nanobind>=2.5.0; extra == "dev"
Requires-Dist: pre-commit>=3.8.0; extra == "dev"
Requires-Dist: scikit-build-core[pyproject]>=0.11.0; extra == "dev"
Dynamic: license-file
